[
  { "id": "research", "name": "Research" },
  { "id": "keyword-research", "name": "Keyword Research" },
  { "id": "audience-discovery", "name": "ICP & Segmentation" },
  { "id": "competitive-analysis", "name": "Competitive Analysis" },
  { "id": "seo-content", "name": "SEO Content & Copywriting" },
  { "id": "ad-creative", "name": "Ad Creative" },
  { "id": "video-generation", "name": "Video Generation" },
  { "id": "image-generation", "name": "Image Generation" },
  { "id": "ugc-creation", "name": "UGC Creation" },
  { "id": "landing-pages", "name": "Landing Pages" },
  { "id": "social-content", "name": "Social Content" },
  { "id": "influencer-discovery", "name": "Influencer Discovery" },
  { "id": "campaign-automation", "name": "Campaign Automation" },
  { "id": "email-marketing", "name": "Email Marketing" },
  { "id": "outreach", "name": "Outreach" },
  { "id": "chatbots", "name": "Chatbots" },
  { "id": "personalization", "name": "Personalization" },
  { "id": "attribution", "name": "Attribution" },
  { "id": "reporting", "name": "Reporting" },
  { "id": "ai-visibility", "name": "GenAI Visibility (GEO)" },
  { "id": "ai-native-media", "name": "AI-Native Media" },
  { "id": "workflow-automation", "name": "Workflow Automation" },
  { "id": "ai-agents", "name": "AI Agents" },
  { "id": "agentic-commerce", "name": "Agentic Commerce" },
  { "id": "sales-automation", "name": "Sales Automation" }
]
